{"nm":"envelope","ddd":0,"h":1080,"w":1080,"meta":{"g":"@lottiefiles/toolkit-js 0.63.0"},"layers":[{"ty":4,"nm":"fingers left Outlines","sr":1,"st":0,"op":750,"ip":0,"ln":"172","hasMask":false,"ao":0,"ks":{"a":{"a":0,"k":[180.606,42.299,0]},"s":{"a":1,"k":[{"s":[0,0,0],"i":{"x":[0.667,0.667,0.667],"y":[1,1,1]},"o":{"x":[0.333,0.333,0.333],"y":[0,0,0]},"t":17},{"s":[120,120,120],"i":{"x":[0.667,0.667,0.667],"y":[1,1,1]},"o":{"x":[0.333,0.333,0.333],"y":[0,0,0]},"t":22},{"s":[100,100,100],"i":{"x":[0.667,0.667,0.667],"y":[1,1,1]},"o":{"x":[0.333,0.333,0.333],"y":[0,0,0]},"t":25}]},"p":{"a":0,"k":[534.694,545.58,0]},"r":{"a":0,"k":0},"o":{"a":0,"k":100}},"shapes":[{"ty":"gr","nm":"Group 1","it":[{"ty":"sh","nm":"Path 1","d":1,"ks":{"a":0,"k":{"c":true,"i":[[6.376,28.721],[-9.417,-4.439],[8.475,-17.84],[14.726,4.409],[-0.05,10.886]],"o":[[0,0],[9.42,4.439],[-8.476,17.84],[0,0],[0,0]],"v":[[-6.646,-29.497],[9.868,-32.428],[17.016,6.838],[-14.553,32.458],[-25.441,20.879]]}}},{"ty":"st","nm":"Stroke 1","lc":2,"lj":2,"ml":4,"o":{"a":0,"k":100},"w":{"a":0,"k":5},"c":{"a":0,"k":[0,0,0]}},{"ty":"fl","nm":"Fill 1","c":{"a":0,"k":[0.9451,0.9216,0.8118]},"r":1,"o":{"a":0,"k":100}},{"ty":"tr","a":{"a":0,"k":[0,0]},"s":{"a":0,"k":[100,100]},"p":{"a":0,"k":[123.221,87.231]},"r":{"a":0,"k":0},"o":{"a":0,"k":100}}]},{"ty":"gr","nm":"Group 2","it":[{"ty":"sh","nm":"Path 1","d":1,"ks":{"a":0,"k":{"c":true,"i":[[8.353,-19.739],[-25.221,13.214],[-1.001,13.976],[6.177,4.729],[13.71,-10.613],[3.483,-12.708]],"o":[[0,0],[18.486,-9.685],[0.556,-7.76],[-6.084,-4.657],[0,0],[-3.484,12.709]],"v":[[-23.875,22.62],[0.418,32.464],[24.247,-18.651],[15.793,-39.017],[-13.513,-35.065],[-13.504,-7.201]]}}},{"ty":"st","nm":"Stroke 1","lc":2,"lj":2,"ml":4,"o":{"a":0,"k":100},"w":{"a":0,"k":5},"c":{"a":0,"k":[0,0,0]}},{"ty":"fl","nm":"Fill 1","c":{"a":0,"k":[0.9451,0.9216,0.8118]},"r":1,"o":{"a":0,"k":100}},{"ty":"tr","a":{"a":0,"k":[0,0]},"s":{"a":0,"k":[100,100]},"p":{"a":0,"k":[92.328,76.386]},"r":{"a":0,"k":0},"o":{"a":0,"k":100}}]},{"ty":"gr","nm":"Group 3","it":[{"ty":"sh","nm":"Path 1","d":1,"ks":{"a":0,"k":{"c":true,"i":[[0,0],[0,0],[-21.705,11.222],[0,0],[26.067,3.89],[0,0],[-5.641,-2.461]],"o":[[-9.858,11.391],[0,0],[21.704,-11.222],[0,0],[-26.066,-3.891],[0,0],[0,0]],"v":[[-0.492,-4.744],[-10.398,19.702],[12.894,38.673],[33.297,-11.681],[6.219,-46.004],[-34.598,-15.84],[-7.248,-3.241]]}}},{"ty":"st","nm":"Stroke 1","lc":2,"lj":2,"ml":4,"o":{"a":0,"k":100},"w":{"a":0,"k":5},"c":{"a":0,"k":[0,0,0]}},{"ty":"fl","nm":"Fill 1","c":{"a":0,"k":[0.9451,0.9216,0.8118]},"r":1,"o":{"a":0,"k":100}},{"ty":"tr","a":{"a":0,"k":[0,0]},"s":{"a":0,"k":[100,100]},"p":{"a":0,"k":[47.098,62.395]},"r":{"a":0,"k":0},"o":{"a":0,"k":100}}]}],"ind":1},{"ty":4,"nm":"fingers right Outlines","sr":1,"st":0,"op":750,"ip":0,"ln":"171","hasMask":false,"ao":0,"ks":{"a":{"a":0,"k":[-18.351,79.86,0]},"s":{"a":1,"k":[{"s":[0,0,0],"i":{"x":[0.667,0.667,0.667],"y":[1,1,1]},"o":{"x":[0.333,0.333,0.333],"y":[0,0,0]},"t":17},{"s":[120,120,120],"i":{"x":[0.667,0.667,0.667],"y":[1,1,1]},"o":{"x":[0.333,0.333,0.333],"y":[0,0,0]},"t":22},{"s":[100,100,100],"i":{"x":[0.667,0.667,0.667],"y":[1,1,1]},"o":{"x":[0.167,0.167,0.167],"y":[0,0,0]},"t":26}]},"p":{"a":0,"k":[537.474,543.182,0]},"r":{"a":0,"k":0},"o":{"a":0,"k":100}},"shapes":[{"ty":"gr","nm":"Group 1","it":[{"ty":"sh","nm":"Path 1","d":1,"ks":{"a":0,"k":{"c":true,"i":[[0,0],[18.811,-9.955],[0,0],[-34.991,19.594],[0,0],[10.085,-8.21]],"o":[[8.375,7.009],[-18.814,9.955],[0,0],[34.992,-19.595],[0,0],[0,0]],"v":[[13.181,-0.891],[19.819,45.086],[-14.477,28.852],[-9.836,-35.446],[44.827,-11.871],[23.377,6.213]]}}},{"ty":"st","nm":"Stroke 1","lc":2,"lj":2,"ml":4,"o":{"a":0,"k":100},"w":{"a":0,"k":5},"c":{"a":0,"k":[0,0,0]}},{"ty":"fl","nm":"Fill 1","c":{"a":0,"k":[0.9451,0.9216,0.8118]},"r":1,"o":{"a":0,"k":100}},{"ty":"tr","a":{"a":0,"k":[0,0]},"s":{"a":0,"k":[100,100]},"p":{"a":0,"k":[93.971,67.541]},"r":{"a":0,"k":0},"o":{"a":0,"k":100}}]},{"ty":"gr","nm":"Group 2","it":[{"ty":"sh","nm":"Path 1","d":1,"ks":{"a":0,"k":{"c":true,"i":[[-29.042,-25.316],[25.518,11.168],[3.581,11.998],[-5.26,7.901],[-12.56,-6.805]],"o":[[0,0],[-16.358,-7.159],[-2.716,-9.095],[4.573,-6.869],[0,0]],"v":[[29.71,17.616],[0.869,32.509],[-26.994,-4.646],[-23.637,-31.64],[1.207,-36.872]]}}},{"ty":"st","nm":"Stroke 1","lc":2,"lj":2,"ml":4,"o":{"a":0,"k":100},"w":{"a":0,"k":5},"c":{"a":0,"k":[0,0,0]}},{"ty":"fl","nm":"Fill 1","c":{"a":0,"k":[0.9451,0.9216,0.8118]},"r":1,"o":{"a":0,"k":100}},{"ty":"tr","a":{"a":0,"k":[0,0]},"s":{"a":0,"k":[100,100]},"p":{"a":0,"k":[64.705,95.331]},"r":{"a":0,"k":0},"o":{"a":0,"k":100}}]},{"ty":"gr","nm":"Group 3","it":[{"ty":"sh","nm":"Path 1","d":1,"ks":{"a":0,"k":{"c":true,"i":[[-28.145,-15.091],[17.502,0.226],[0,0],[-1.022,10.599],[-8.65,1.216],[-2.372,-0.667]],"o":[[0,0],[-17.502,-0.226],[0,0],[0.838,-8.693],[2.088,-0.292],[0,0]],"v":[[25.848,16.429],[9.724,31.583],[-21.478,5.968],[-26.204,-14.025],[-10.273,-31.517],[-3.532,-31.088]]}}},{"ty":"st","nm":"Stroke 1","lc":2,"lj":2,"ml":4,"o":{"a":0,"k":100},"w":{"a":0,"k":5},"c":{"a":0,"k":[0,0,0]}},{"ty":"fl","nm":"Fill 1","c":{"a":0,"k":[0.9451,0.9216,0.8118]},"r":1,"o":{"a":0,"k":100}},{"ty":"tr","a":{"a":0,"k":[0,0]},"s":{"a":0,"k":[100,100]},"p":{"a":0,"k":[39.726,111.411]},"r":{"a":0,"k":0},"o":{"a":0,"k":100}}]}],"ind":2},{"ty":4,"nm":"front envelope Outlines","sr":1,"st":0,"op":750,"ip":0,"ln":"170","hasMask":false,"ao":0,"ks":{"a":{"a":0,"k":[369.563,156.214,0]},"s":{"a":1,"k":[{"s":[0,0,0],"i":{"x":[0.667,0.667,0.667],"y":[1,1,1]},"o":{"x":[0.333,0.333,0.333],"y":[0,0,0]},"t":17},{"s":[120,120,120],"i":{"x":[0.667,0.667,0.667],"y":[1,1,1]},"o":{"x":[0.333,0.333,0.333],"y":[0,0,0]},"t":22},{"s":[100,100,100],"i":{"x":[0.667,0.667,0.667],"y":[1,1,1]},"o":{"x":[0.167,0.167,0.167],"y":[0,0,0]},"t":26}]},"p":{"a":0,"k":[537.621,544.661,0]},"r":{"a":0,"k":0},"o":{"a":0,"k":100}},"shapes":[{"ty":"gr","nm":"Group 1","it":[{"ty":"sh","nm":"Path 1","d":1,"ks":{"a":0,"k":{"c":true,"i":[[0,0],[13.904,7.128],[0,0],[-3.398,-33.399],[0,0],[-23.05,-16.805],[-7.056,6.758]],"o":[[10.5,-11.572],[0,0],[-8.964,20.031],[7.426,72.989],[0,0],[5.227,-1.702],[0,0]],"v":[[151.395,-34.077],[144.645,-71.159],[-145.572,-210.017],[-158.497,-129.155],[-110.861,169.45],[-85.738,210.018],[-66.648,197.791]]}}},{"ty":"st","nm":"Stroke 1","lc":1,"lj":1,"ml":10,"o":{"a":0,"k":100},"w":{"a":0,"k":5},"c":{"a":0,"k":[0,0,0]}},{"ty":"fl","nm":"Fill 1","c":{"a":0,"k":[0.702,0.5765,0.9412]},"r":1,"o":{"a":0,"k":100}},{"ty":"tr","a":{"a":0,"k":[0,0]},"s":{"a":0,"k":[100,100]},"p":{"a":0,"k":[174.395,290.424]},"r":{"a":0,"k":0},"o":{"a":0,"k":100}}]},{"ty":"gr","nm":"Group 2","it":[{"ty":"sh","nm":"Path 1","d":1,"ks":{"a":0,"k":{"c":true,"i":[[2.185,36.588],[11.654,72.04],[15.597,21.742],[0,0],[-12.923,-8.781],[0,0],[-4.011,-1.32]],"o":[[-4.799,-80.397],[-4.373,-27.029],[0,0],[-11.84,10.195],[0,0],[1.359,0.888],[10.115,-13.992]],"v":[[151.185,129.923],[123.498,-129.117],[92.881,-203.123],[-141.53,-12.27],[-139.383,25.361],[127.016,199.537],[135.824,203.123]]}}},{"ty":"st","nm":"Stroke 1","lc":1,"lj":1,"ml":10,"o":{"a":0,"k":100},"w":{"a":0,"k":5},"c":{"a":0,"k":[0,0,0]}},{"ty":"fl","nm":"Fill 1","c":{"a":0,"k":[0.702,0.5765,0.9412]},"r":1,"o":{"a":0,"k":100}},{"ty":"tr","a":{"a":0,"k":[0,0]},"s":{"a":0,"k":[100,100]},"p":{"a":0,"k":[577.256,215.623]},"r":{"a":0,"k":0},"o":{"a":0,"k":100}}]},{"ty":"gr","nm":"Group 3","it":[{"ty":"sh","nm":"Path 1","d":1,"ks":{"a":0,"k":{"c":true,"i":[[-62.154,10.326],[0,0],[-14.602,42.589],[20.028,7.555],[27.109,-9.252],[60.309,-84.323]],"o":[[106.993,-17.776],[0,0],[-67.695,-53.822],[-23.807,-8.98],[-20.242,6.908],[14.473,17.544]],"v":[[-216.305,144.285],[272.355,72.099],[322.945,30.25],[67.484,-145.631],[-88.659,-132.858],[-322.945,120.071]]}}},{"ty":"st","nm":"Stroke 1","lc":1,"lj":1,"ml":10,"o":{"a":0,"k":100},"w":{"a":0,"k":5},"c":{"a":0,"k":[0,0,0]}},{"ty":"fl","nm":"Fill 1","c":{"a":0,"k":[0.702,0.5765,0.9412]},"r":1,"o":{"a":0,"k":100}},{"ty":"tr","a":{"a":0,"k":[0,0]},"s":{"a":0,"k":[100,100]},"p":{"a":0,"k":[399.814,369.316]},"r":{"a":0,"k":0},"o":{"a":0,"k":100}}]}],"ind":3},{"ty":4,"nm":"face Outlines","sr":1,"st":0,"op":750,"ip":0,"ln":"169","hasMask":false,"ao":0,"ks":{"a":{"a":0,"k":[158.273,129.448,0]},"s":{"a":1,"k":[{"s":[0,0,0],"i":{"x":[0.667,0.667,0.667],"y":[1,1,1]},"o":{"x":[0.333,0.333,0.333],"y":[0,0,0]},"t":17},{"s":[120,120,120],"i":{"x":[0.667,0.667,0.667],"y":[1,1,1]},"o":{"x":[0.333,0.333,0.333],"y":[0,0,0]},"t":22},{"s":[100,100,100],"i":{"x":[0.667,0.667,0.667],"y":[1,1,1]},"o":{"x":[0.167,0.167,0.167],"y":[0,0,0]},"t":26}]},"p":{"a":0,"k":[538.854,543.611,0]},"r":{"a":0,"k":0},"o":{"a":0,"k":100}},"shapes":[{"ty":"gr","nm":"Group 1","it":[{"ty":"sh","nm":"Path 1","d":1,"ks":{"a":0,"k":{"c":false,"i":[[0,0],[-27.019,4.685],[0,0]],"o":[[0,0],[27.018,-4.685],[0,0]],"v":[[-29.872,-7.659],[2.854,13.25],[27.499,-17.935]]}}},{"ty":"st","nm":"Stroke 1","lc":2,"lj":2,"ml":4,"o":{"a":0,"k":100},"w":{"a":0,"k":5},"c":{"a":0,"k":[0,0,0]}},{"ty":"tr","a":{"a":0,"k":[0,0]},"s":{"a":0,"k":[100,100]},"p":{"a":0,"k":[155.822,128.461]},"r":{"a":0,"k":0},"o":{"a":0,"k":100}}]},{"ty":"gr","nm":"Group 2","it":[{"ty":"sh","nm":"Path 1","d":1,"ks":{"a":0,"k":{"c":true,"i":[[1.908,13.996],[21.877,-3.257],[-4.819,-35.364],[-5.822,-9.669],[-21.585,3.566]],"o":[[-4.819,-35.364],[-21.875,3.258],[1.839,13.501],[21.586,-3.47],[3.276,-11.239]],"v":[[41.065,7.151],[-7.27,-50.983],[-38.154,18.949],[-26.19,54.24],[38.645,45.712]]}}},{"ty":"fl","nm":"Fill 1","c":{"a":0,"k":[0,0,0]},"r":1,"o":{"a":0,"k":100}},{"ty":"tr","a":{"a":0,"k":[0,0]},"s":{"a":0,"k":[100,100]},"p":{"a":0,"k":[43.223,83.476]},"r":{"a":0,"k":0},"o":{"a":0,"k":100}}]},{"ty":"gr","nm":"Group 3","it":[{"ty":"sh","nm":"Path 1","d":1,"ks":{"a":0,"k":{"c":true,"i":[[1.907,13.996],[21.877,-3.257],[-4.82,-35.364],[-5.822,-9.669],[-21.584,3.566]],"o":[[-4.819,-35.364],[-21.875,3.258],[1.839,13.501],[21.587,-3.47],[3.277,-11.239]],"v":[[41.066,7.151],[-7.27,-50.983],[-38.153,18.949],[-26.19,54.24],[38.645,45.712]]}}},{"ty":"fl","nm":"Fill 1","c":{"a":0,"k":[0,0,0]},"r":1,"o":{"a":0,"k":100}},{"ty":"tr","a":{"a":0,"k":[0,0]},"s":{"a":0,"k":[100,100]},"p":{"a":0,"k":[253.323,54.49]},"r":{"a":0,"k":0},"o":{"a":0,"k":100}}]}],"ind":4},{"ty":4,"nm":"letter Outlines","sr":1,"st":0,"op":750,"ip":0,"ln":"168","hasMask":false,"ao":0,"ks":{"a":{"a":0,"k":[372.391,302.184,0]},"s":{"a":1,"k":[{"s":[0,0,0],"i":{"x":[0.667,0.667,0.667],"y":[1,1,1]},"o":{"x":[0.333,0.333,0.333],"y":[0,0,0]},"t":17},{"s":[120,120,120],"i":{"x":[0.667,0.667,0.667],"y":[1,1,1]},"o":{"x":[0.333,0.333,0.333],"y":[0,0,0]},"t":22},{"s":[100,100,100],"i":{"x":[0.667,0.667,0.667],"y":[1,1,1]},"o":{"x":[0.167,0.167,0.167],"y":[0,0,0]},"t":26}]},"p":{"a":0,"k":[535.422,546.051,0]},"r":{"a":0,"k":0},"o":{"a":0,"k":100}},"shapes":[{"ty":"gr","nm":"Group 1","it":[{"ty":"sh","nm":"Path 1","d":1,"ks":{"a":0,"k":{"c":true,"i":[[0,0],[-134.304,-79.33],[0,0],[0,0],[-48.377,186.459]],"o":[[-74.229,126.894],[0,0],[0,0],[-51.491,-39.428],[0,0]],"v":[[-269.662,-168.141],[-147.359,235.684],[278.389,219.674],[343.891,30.843],[245.979,-235.684]]}}},{"ty":"st","nm":"Stroke 1","lc":2,"lj":2,"ml":4,"o":{"a":0,"k":100},"w":{"a":0,"k":5},"c":{"a":0,"k":[0,0,0]}},{"ty":"fl","nm":"Fill 1","c":{"a":0,"k":[0.9451,0.9216,0.8118]},"r":1,"o":{"a":0,"k":100}},{"ty":"tr","a":{"a":0,"k":[0,0]},"s":{"a":0,"k":[100,100]},"p":{"a":0,"k":[356.391,248.184]},"r":{"a":0,"k":0},"o":{"a":0,"k":100}}]}],"ind":5},{"ty":4,"nm":"back envelope Outlines","sr":1,"st":0,"op":750,"ip":0,"ln":"167","hasMask":false,"ao":0,"ks":{"a":{"a":0,"k":[371.387,375.395,0]},"s":{"a":1,"k":[{"s":[0,0,0],"i":{"x":[0.667,0.667,0.667],"y":[1,1,1]},"o":{"x":[0.333,0.333,0.333],"y":[0,0,0]},"t":17},{"s":[120,120,120],"i":{"x":[0.667,0.667,0.667],"y":[1,1,1]},"o":{"x":[0.333,0.333,0.333],"y":[0,0,0]},"t":22},{"s":[100,100,100],"i":{"x":[0.667,0.667,0.667],"y":[1,1,1]},"o":{"x":[0.167,0.167,0.167],"y":[0,0,0]},"t":26}]},"p":{"a":0,"k":[535.418,546.054,0]},"r":{"a":0,"k":0},"o":{"a":0,"k":100}},"shapes":[{"ty":"gr","nm":"Group 1","it":[{"ty":"sh","nm":"Path 1","d":1,"ks":{"a":0,"k":{"c":true,"i":[[0,0],[17.818,-16.819],[0,0],[-7.426,-72.988],[0,0],[-113.764,18.9],[0,0],[5.805,97.233],[11.655,72.041],[43.755,26.659]],"o":[[-20.924,-12.749],[0,0],[0,0],[7.426,72.988],[0,0],[106.993,-17.776],[0,0],[-4.799,-80.397],[-8.183,-50.578],[0,0]],"v":[[-10.823,-356.146],[-76.431,-349.253],[-319.025,-120.251],[-355.461,-2.337],[-307.824,296.267],[-187.851,349.995],[300.809,277.809],[357.082,181.94],[329.395,-77.101],[247.481,-198.762]]}}},{"ty":"st","nm":"Stroke 1","lc":1,"lj":1,"ml":10,"o":{"a":0,"k":100},"w":{"a":0,"k":5},"c":{"a":0,"k":[0,0,0]}},{"ty":"fl","nm":"Fill 1","c":{"a":0,"k":[0.702,0.5765,0.9412]},"r":1,"o":{"a":0,"k":100}},{"ty":"tr","a":{"a":0,"k":[0,0]},"s":{"a":0,"k":[100,100]},"p":{"a":0,"k":[375.386,381.395]},"r":{"a":0,"k":0},"o":{"a":0,"k":100}}]}],"ind":6},{"ty":4,"nm":"white background Outlines 2","sr":1,"st":0,"op":750,"ip":0,"ln":"173","hasMask":false,"ao":0,"ks":{"a":{"a":0,"k":[419.981,420.377,0]},"s":{"a":1,"k":[{"s":[0,0,0],"i":{"x":[0.667,0.667,0.667],"y":[1,1,1]},"o":{"x":[0.333,0.333,0.333],"y":[0,0,0]},"t":17},{"s":[120,120,120],"i":{"x":[0.667,0.667,0.667],"y":[1,1,1]},"o":{"x":[0.333,0.333,0.333],"y":[0,0,0]},"t":22},{"s":[100,100,100],"i":{"x":[0.667,0.667,0.667],"y":[1,1,1]},"o":{"x":[0.167,0.167,0.167],"y":[0,0,0]},"t":26}]},"p":{"a":0,"k":[538.67,540.286,0]},"r":{"a":0,"k":0},"o":{"a":0,"k":100}},"shapes":[{"ty":"gr","nm":"Group 1","it":[{"ty":"sh","nm":"Path 1","d":1,"ks":{"a":0,"k":{"c":false,"i":[[0,0],[1.415,10.478],[7.2,70.883],[-19.595,36.869],[-4.534,6.258],[-19.759,37.194],[0,0],[0,0],[0,0],[-27.596,0],[-16.878,-10.299],[0,0],[0,0],[0,0],[4.272,-15.238],[0,0],[-17.053,-22.142],[-3.604,-7.837],[-4.394,-27.194],[-4.922,-82.519],[2.456,-14.9],[15.576,-17.005],[26.214,-1.467],[98.734,-16.425],[13.599,0],[17.57,20.52]],"o":[[-19.608,-22.903],[-3.747,-21.108],[-4.249,-41.806],[5.165,-9.72],[1.82,-35.474],[0,0],[0,0],[0,0],[20.06,-18.96],[19.754,0],[0,0],[0,0],[0,0],[-0.058,0.156],[0,0],[23.815,14.535],[8.198,8.154],[13.736,23.863],[11.491,71.113],[1.046,17.522],[-1.066,12.681],[-22.238,34.846],[-35.143,5.024],[-15.27,2.541],[-59.675,0],[0,0]],"v":[[-329.689,362.89],[-356.007,305.672],[-403.232,8.579],[-379.772,-111.68],[-364.808,-135.725],[-332.356,-245.069],[-319.267,-269.704],[-211.862,-283.792],[-111.699,-378.472],[-37.799,-407.877],[18.193,-392.136],[123.642,-327.8],[304.868,-351.571],[274.082,-267.594],[265.733,-241.106],[272.63,-236.899],[334.178,-181.661],[351.248,-156.214],[378.562,-79.298],[406.435,181.632],[404.309,230.466],[384.899,283.216],[301.771,333.448],[-175.465,404.048],[-218.97,407.877],[-329.686,362.893]]}}},{"ty":"st","nm":"Stroke 1","lc":2,"lj":2,"ml":4,"o":{"a":0,"k":100},"w":{"a":0,"k":5},"c":{"a":0,"k":[0,0,0]}},{"ty":"fl","nm":"Fill 1","c":{"a":0,"k":[1,1,1]},"r":1,"o":{"a":0,"k":100}},{"ty":"tr","a":{"a":0,"k":[0,0]},"s":{"a":0,"k":[100,100]},"p":{"a":0,"k":[419.981,420.377]},"r":{"a":0,"k":0},"o":{"a":0,"k":100}}]}],"ind":7},{"ty":4,"nm":"white background Outlines","sr":1,"st":0,"op":750,"ip":0,"ln":"166","hasMask":false,"ao":0,"ks":{"a":{"a":0,"k":[419.981,420.377,0]},"s":{"a":0,"k":[100,100]},"p":{"a":0,"k":[538.67,540.286,0]},"r":{"a":0,"k":0},"o":{"a":0,"k":100}},"shapes":[{"ty":"gr","nm":"Group 1","it":[{"ty":"sh","nm":"Path 1","d":1,"ks":{"a":0,"k":{"c":false,"i":[[0,0],[1.415,10.478],[7.2,70.883],[-19.595,36.869],[-4.534,6.258],[-19.759,37.194],[0,0],[0,0],[0,0],[-27.596,0],[-16.878,-10.299],[0,0],[0,0],[0,0],[4.272,-15.238],[0,0],[-17.053,-22.142],[-3.604,-7.837],[-4.394,-27.194],[-4.922,-82.519],[2.456,-14.9],[15.576,-17.005],[26.214,-1.467],[98.734,-16.425],[13.599,0],[17.57,20.52]],"o":[[-19.608,-22.903],[-3.747,-21.108],[-4.249,-41.806],[5.165,-9.72],[1.82,-35.474],[0,0],[0,0],[0,0],[20.06,-18.96],[19.754,0],[0,0],[0,0],[0,0],[-0.058,0.156],[0,0],[23.815,14.535],[8.198,8.154],[13.736,23.863],[11.491,71.113],[1.046,17.522],[-1.066,12.681],[-22.238,34.846],[-35.143,5.024],[-15.27,2.541],[-59.675,0],[0,0]],"v":[[-329.689,362.89],[-356.007,305.672],[-403.232,8.579],[-379.772,-111.68],[-364.808,-135.725],[-332.356,-245.069],[-319.267,-269.704],[-211.862,-283.792],[-111.699,-378.472],[-37.799,-407.877],[18.193,-392.136],[123.642,-327.8],[304.868,-351.571],[274.082,-267.594],[265.733,-241.106],[272.63,-236.899],[334.178,-181.661],[351.248,-156.214],[378.562,-79.298],[406.435,181.632],[404.309,230.466],[384.899,283.216],[301.771,333.448],[-175.465,404.048],[-218.97,407.877],[-329.686,362.893]]}}},{"ty":"st","nm":"Stroke 1","lc":2,"lj":2,"ml":4,"o":{"a":0,"k":100},"w":{"a":0,"k":5},"c":{"a":0,"k":[0,0,0]}},{"ty":"fl","nm":"Fill 1","c":{"a":0,"k":[1,1,1]},"r":1,"o":{"a":0,"k":100}},{"ty":"tr","a":{"a":0,"k":[0,0]},"s":{"a":0,"k":[100,100]},"p":{"a":0,"k":[419.981,420.377]},"r":{"a":0,"k":0},"o":{"a":0,"k":100}}]}],"ind":8}],"v":"5.7.0","fr":25,"op":750,"ip":0,"assets":[]}